{
  "globalStyle": {
    "navigationBarBackgroundColor": "@navBgColor",
    "navigationBarTextStyle": "@navTxtStyle",
    "navigationBarTitleText": "Wot Starter",
    "backgroundColor": "@bgColor",
    "backgroundTextStyle": "@bgTxtStyle",
    "backgroundColorTop": "@bgColorTop",
    "backgroundColorBottom": "@bgColorBottom",
    "enablePullDownRefresh": false,
    "onReachBottomDistance": 50,
    "animationType": "pop-in",
    "animationDuration": 300
  },
  "pages": [
    // GENERATED BY UNI-PAGES, PLATFORM: MP-WEIXIN
    {
      "path": "pages/index/index",
      "type": "home",
      "name": "index",
      "layout": "tabbar",
      "style": {
        "navigationBarTitleText": "首页",
        "navigationStyle": "custom",
        "enablePullDownRefresh": true
      }
    },
    {
      "path": "pages/login/login",
      "type": "page",
      "name": "login",
      "layout": "default",
      "style": {
        "navigationBarTitleText": "登录",
        "navigationStyle": "custom"
      }
    },
    {
      "path": "pages/me/me",
      "type": "page",
      "name": "me",
      "layout": "tabbar",
      "style": {
        "navigationBarTitleText": "我的",
        "navigationStyle": "custom"
      }
    }
  ],
  "subPackages": [],
  "tabBar": {
    "custom": true,
    "customize": true,
    "overlay": true,
    "height": "0",
    "color": "@tabColor",
    "selectedColor": "@tabSelectedColor",
    "backgroundColor": "@tabBgColor",
    "borderStyle": "@tabBorderStyle",
    "list": [
      // GENERATED BY UNI-PAGES, PLATFORM: MP-WEIXIN
      {
        "pagePath": "pages/index/index"
      },
      {
        "pagePath": "pages/me/me"
      }
    ]
  }
}
